bindable/__init__.py
bindable/_main.py
bindable/py.typed
bindable-0.0.7.dist-info/METADATA
bindable-0.0.7.dist-info/WHEEL
bindable-0.0.7.dist-info/licenses/LICENSE
bindable-0.0.7.dist-info/RECORD
