Metadata-Version: 2.4
Name: bindable
Version: 0.0.7
Summary: Package for bindable singleton objects in Python. They act similar to Angular Services.
Project-URL: Homepage, https://github.com/Snowcaloid/py-bindable
Project-URL: Issues, https://github.com/Snowcaloid/py-bindable/issues
Author-email: Snowcaloid <dev.snowcaloid@gmail.com>
License-File: LICENSE
Classifier: Operating System :: OS Independent
Classifier: Programming Language :: Python :: 3
Requires-Python: >=3.13.2
